{
  "playlists": [
    {
      "name": "我踏遍千山万水，只为遇见你",
      "id": 930119864,
      "trackNumberUpdateTime": 1506169925965,
      "status": 0,
      "userId": 55997709,
      "createTime": 1506165529207,
      "updateTime": 1508152932738,
      "subscribedCount": 302,
      "trackCount": 26,
      "cloudTrackCount": 0,
      "coverImgUrl": "http://p1.music.126.net/33W2NxxBkW9CJXYYA54qxw==/109951163030368631.jpg",
      "coverImgId": 109951163030368631,
      "description": "你是我的晴天\n你是我的阳光\n你是我的氧气\n\n你是我的药\n你是我的OK绷\n你是我的天使\n\n你是年少的欢喜\n你是明日的意义\n你是我心内的一首歌\n\n你是我的风景\n你是我的虚荣\n你是我最愚蠢的一次浪漫\n\n你是我的命运\n你是我的梦想\n你是我的意义\n\n你是我的主角\n你是我的唯一\n你是我最爱的女人\n\n遇上你是我的缘\n你是如此难以忘记\n\n所有的欢笑与泪水\n都是与你相遇的理由",
      "tags": [
        "华语",
        "流行",
        "伤感"
      ],
      "playCount": 71570,
      "trackUpdateTime": 1508314539187,
      "specialType": 0,
      "totalDuration": 0,
      "creator": {
        "defaultAvatar": false,
        "province": 330000,
        "authStatus": 0,
        "followed": false,
        "avatarUrl": "http://p1.music.126.net/WZkzn6pKklGThuJpUbB_BQ==/109951162849189532.jpg",
        "accountStatus": 0,
        "gender": 1,
        "city": 330100,
        "birthday": -2209017600000,
        "userId": 55997709,
        "userType": 0,
        "nickname": "A_Mraz_ing",
        "signature": "我是白羊座的 就这样~",
        "description": "",
        "detailDescription": "",
        "avatarImgId": 109951162849189532,
        "backgroundImgId": 109951162950184519,
        "backgroundUrl": "http://p1.music.126.net/mMxhQRXOHclScWr4pZiC5A==/109951162950184519.jpg",
        "authority": 0,
        "mutual": false,
        "expertTags": null,
        "experts": null,
        "djStatus": 0,
        "vipType": 0,
        "remarkName": null,
        "avatarImgIdStr": "109951162849189532",
        "backgroundImgIdStr": "109951162950184519",
        "avatarImgId_str": "109951162849189532"
      },
      "tracks": null,
      "subscribers": [
        {
          "defaultAvatar": false,
          "province": 320000,
          "authStatus": 0,
          "followed": false,
          "avatarUrl": "http://p1.music.126.net/fm8QbDKPHjaXPEECDqR2ew==/1400777830883751.jpg",
          "accountStatus": 0,
          "gender": 2,
          "city": 320600,
          "birthday": -2209017600000,
          "userId": 352888579,
          "userType": 0,
          "nickname": "初衷abc",
          "signature": "",
          "description": "",
          "detailDescription": "",
          "avatarImgId": 1400777830883751,
          "backgroundImgId": 2002210674180202,
          "backgroundUrl": "http://p1.music.126.net/pmHS4fcQtcNEGewNb5HRhg==/2002210674180202.jpg",
          "authority": 0,
          "mutual": false,
          "expertTags": null,
          "experts": null,
          "djStatus": 0,
          "vipType": 0,
          "remarkName": null,
          "avatarImgIdStr": "1400777830883751",
          "backgroundImgIdStr": "2002210674180202"
        }
      ],
      "subscribed": null,
      "commentThreadId": "A_PL_0_930119864",
      "newImported": false,
      "adType": 0,
      "highQuality": false,
      "privacy": 0,
      "ordered": true,
      "anonimous": false,
      "shareCount": 5,
      "coverImgId_str": "109951163030368631",
      "commentCount": 6
    },
    {
      "name": "爵士音乐大师•精妙的合作•融合与创新",
      "id": 884060640,
      "trackNumberUpdateTime": 1507464442234,
      "status": 0,
      "userId": 350556138,
      "createTime": 1502976789186,
      "updateTime": 1507464442234,
      "subscribedCount": 84,
      "trackCount": 124,
      "cloudTrackCount": 0,
      "coverImgUrl": "http://p1.music.126.net/LYWNnL0jVUSRpcp8AeueSQ==/18944585346897245.jpg",
      "coverImgId": 18944585346897245,
      "description": "爵士萨克斯，吉他，贝斯，爵士鼓大师们能摩擦出什么样的火花呢？\n歌单收录爵士音乐大师合作精品曲目，敬请欣赏。",
      "tags": [
        "爵士",
        "蓝调",
        "世界音乐"
      ],
      "playCount": 11116,
      "trackUpdateTime": 1507464446246,
      "specialType": 0,
      "totalDuration": 0,
      "creator": {
        "defaultAvatar": false,
        "province": 210000,
        "authStatus": 0,
        "followed": false,
        "avatarUrl": "http://p1.music.126.net/3njktKVbX1IVHJlvwfpwQQ==/109951163018167604.jpg",
        "accountStatus": 0,
        "gender": 1,
        "city": 210200,
        "birthday": 791049600000,
        "userId": 350556138,
        "userType": 0,
        "nickname": "Melody_Groove",
        "signature": "Melody&Groove音乐工作室•音乐制作人•Line1乐队吉他手•Swing H爵士乐队贝司手•Pop Rock Blues Jazz Funk Latin Swing Fusion.",
        "description": "",
        "detailDescription": "",
        "avatarImgId": 109951163018167604,
        "backgroundImgId": 109951163018145362,
        "backgroundUrl": "http://p1.music.126.net/Vxu7E0IX3O8nh1HCVR3AeQ==/109951163018145362.jpg",
        "authority": 0,
        "mutual": false,
        "expertTags": [
          "蓝调",
          "爵士",
          "摇滚"
        ],
        "experts": null,
        "djStatus": 0,
        "vipType": 11,
        "remarkName": null,
        "avatarImgIdStr": "109951163018167604",
        "backgroundImgIdStr": "109951163018145362",
        "avatarImgId_str": "109951163018167604"
      },
      "tracks": null,
      "subscribers": [
        {
          "defaultAvatar": false,
          "province": 440000,
          "authStatus": 0,
          "followed": false,
          "avatarUrl": "http://p1.music.126.net/7HrU774tKa5UGcB0tW_yPA==/18875316114326249.jpg",
          "accountStatus": 0,
          "gender": 1,
          "city": 441900,
          "birthday": 971835903234,
          "userId": 476193545,
          "userType": 0,
          "nickname": "枫林似焰",
          "signature": "",
          "description": "",
          "detailDescription": "",
          "avatarImgId": 18875316114326249,
          "backgroundImgId": 19019352137650967,
          "backgroundUrl": "http://p1.music.126.net/KDyHmPZ17trk5qHHldV4_Q==/19019352137650967.jpg",
          "authority": 0,
          "mutual": false,
          "expertTags": null,
          "experts": null,
          "djStatus": 0,
          "vipType": 0,
          "remarkName": null,
          "avatarImgIdStr": "18875316114326249",
          "backgroundImgIdStr": "19019352137650967",
          "avatarImgId_str": "18875316114326249"
        }
      ],
      "subscribed": null,
      "commentThreadId": "A_PL_0_884060640",
      "newImported": false,
      "adType": 0,
      "highQuality": false,
      "privacy": 0,
      "ordered": true,
      "anonimous": false,
      "shareCount": 1,
      "coverImgId_str": "18944585346897245",
      "commentCount": 0
    },
    {
      "name": "粤语｜看星星 一处渐渐繁华 时光不留人",
      "id": 803701908,
      "trackNumberUpdateTime": 1508294240234,
      "status": 0,
      "userId": 325726984,
      "createTime": 1499567237617,
      "updateTime": 1508294240234,
      "subscribedCount": 153,
      "trackCount": 31,
      "cloudTrackCount": 0,
      "coverImgUrl": "http://p1.music.126.net/WU0TJGcJgvGeV4jBeK6cnw==/19011655556275690.jpg",
      "coverImgId": 19011655556275690,
      "description": "歌单标题来源连诗雅的《旧街角》的歌词，这首歌讲述在旧街角与前任偶遇的故事。\n\n在物是人非的时光里，只有记忆在作祟。来到以前的街，就像曾经一样，仍旧是陌生的人来人往，好似还是那天，我们穿梭在陌生的人潮里，仿佛那才是正经要紧的事情，两只手紧紧的牵着，像约定的一样不分开，那瞬间就觉得永远好像也不远。\n\n多年后 看星星 一处渐渐繁华 时光却不留人\n\n封面:连诗雅",
      "tags": [
        "粤语",
        "流行",
        "感动"
      ],
      "playCount": 18869,
      "trackUpdateTime": 1508294486380,
      "specialType": 0,
      "totalDuration": 0,
      "creator": {
        "defaultAvatar": false,
        "province": 440000,
        "authStatus": 0,
        "followed": false,
        "avatarUrl": "http://p1.music.126.net/XwkgvX08bmvuhiLnY7jD8g==/18727981557994394.jpg",
        "accountStatus": 0,
        "gender": 0,
        "city": 440100,
        "birthday": 857989440553,
        "userId": 325726984,
        "userType": 0,
        "nickname": "Eddie-Fannie",
        "signature": "97男孩生于潮汕，长于广州｜一切好听的音乐都是饲养耳朵的高级肥料｜好看的人长得千篇一律，容易被骗的白富美却寥寥无几｜原ID-Eddie-你的半杯可乐",
        "description": "",
        "detailDescription": "",
        "avatarImgId": 18727981557994394,
        "backgroundImgId": 19210667160898026,
        "backgroundUrl": "http://p1.music.126.net/oqCuiQpbnAA0KYd8-wgfaA==/19210667160898026.jpg",
        "authority": 0,
        "mutual": false,
        "expertTags": [
          "华语",
          "流行"
        ],
        "experts": {
          "1": "视频达人"
        },
        "djStatus": 0,
        "vipType": 0,
        "remarkName": null,
        "avatarImgIdStr": "18727981557994394",
        "backgroundImgIdStr": "19210667160898026",
        "avatarImgId_str": "18727981557994394"
      },
      "tracks": null,
      "subscribers": [
        {
          "defaultAvatar": false,
          "province": 320000,
          "authStatus": 0,
          "followed": false,
          "avatarUrl": "http://p1.music.126.net/-6Qci3BBUifDZZefBdw1hw==/1374389546844901.jpg",
          "accountStatus": 0,
          "gender": 2,
          "city": 320200,
          "birthday": -2209017600000,
          "userId": 295944712,
          "userType": 0,
          "nickname": "再见了小鳄鱼",
          "signature": "",
          "description": "",
          "detailDescription": "",
          "avatarImgId": 1374389546844901,
          "backgroundImgId": 2002210674180202,
          "backgroundUrl": "http://p1.music.126.net/pmHS4fcQtcNEGewNb5HRhg==/2002210674180202.jpg",
          "authority": 0,
          "mutual": false,
          "expertTags": null,
          "experts": null,
          "djStatus": 0,
          "vipType": 0,
          "remarkName": null,
          "avatarImgIdStr": "1374389546844901",
          "backgroundImgIdStr": "2002210674180202"
        }
      ],
      "subscribed": null,
      "commentThreadId": "A_PL_0_803701908",
      "newImported": false,
      "adType": 0,
      "highQuality": false,
      "privacy": 0,
      "ordered": true,
      "anonimous": false,
      "shareCount": 1,
      "coverImgId_str": "19011655556275690",
      "commentCount": 8
    },
    {
      "name": "【复古】不独特，我只是千禧一代",
      "id": 752752169,
      "trackNumberUpdateTime": 1508040018346,
      "status": 0,
      "userId": 284212473,
      "createTime": 1496714185992,
      "updateTime": 1508040018346,
      "subscribedCount": 50,
      "trackCount": 28,
      "cloudTrackCount": 0,
      "coverImgUrl": "http://p1.music.126.net/SWUnjOME03MqB6ZQaPyr-A==/109951163040691925.jpg",
      "coverImgId": 109951163040691925,
      "description": "千禧一代（Millennials），指1984-2000年出生的人，以不安全、自我和高消费为特点，重视友情与家庭.\n\n九十年出生的孩子们见证了朵朵奇葩开了又落\n国门打开最先吹来的音乐潮流便是迪斯科了\n还记得当时那套“冲击波”音乐系列吗？\n一起来回味一下吧！\n\n致幻剂：90年代 迪斯科 Funk",
      "tags": [
        "舞曲",
        "怀旧",
        "90后"
      ],
      "playCount": 6601,
      "trackUpdateTime": 1508060743947,
      "specialType": 0,
      "totalDuration": 0,
      "creator": {
        "defaultAvatar": false,
        "province": 1000000,
        "authStatus": 0,
        "followed": false,
        "avatarUrl": "http://p1.music.126.net/du2kJoYvF4z_Ms_bpDGHig==/109951163040656791.jpg",
        "accountStatus": 0,
        "gender": 2,
        "city": 1006600,
        "birthday": -1357113600000,
        "userId": 284212473,
        "userType": 0,
        "nickname": "M_H_V_L_S",
        "signature": "这里是 无妄星球",
        "description": "",
        "detailDescription": "",
        "avatarImgId": 109951163040656791,
        "backgroundImgId": 109951163040660850,
        "backgroundUrl": "http://p1.music.126.net/8NCJu7yVtYOk6WTax9YcCQ==/109951163040660850.jpg",
        "authority": 0,
        "mutual": false,
        "expertTags": null,
        "experts": null,
        "djStatus": 10,
        "vipType": 10,
        "remarkName": null,
        "avatarImgIdStr": "109951163040656791",
        "backgroundImgIdStr": "109951163040660850",
        "avatarImgId_str": "109951163040656791"
      },
      "tracks": null,
      "subscribers": [
        {
          "defaultAvatar": false,
          "province": 130000,
          "authStatus": 0,
          "followed": false,
          "avatarUrl": "http://p1.music.126.net/qdyAWZQ5rX4qzPTWp4ayKQ==/18621328929949047.jpg",
          "accountStatus": 0,
          "gender": 1,
          "city": 130100,
          "birthday": -2209017600000,
          "userId": 492701083,
          "userType": 0,
          "nickname": "李赜文",
          "signature": "",
          "description": "",
          "detailDescription": "",
          "avatarImgId": 18621328929949047,
          "backgroundImgId": 19127104277130964,
          "backgroundUrl": "http://p1.music.126.net/trZ3lq7G_ZfOLZKT-sN2rg==/19127104277130964.jpg",
          "authority": 0,
          "mutual": false,
          "expertTags": null,
          "experts": null,
          "djStatus": 0,
          "vipType": 0,
          "remarkName": null,
          "avatarImgIdStr": "18621328929949047",
          "backgroundImgIdStr": "19127104277130964",
          "avatarImgId_str": "18621328929949047"
        }
      ],
      "subscribed": null,
      "commentThreadId": "A_PL_0_752752169",
      "newImported": false,
      "adType": 0,
      "highQuality": false,
      "privacy": 0,
      "ordered": true,
      "anonimous": false,
      "shareCount": 4,
      "coverImgId_str": "109951163040691925",
      "commentCount": 1
    },
    {
      "name": "[二次元女声]邂逅是场来之不易的美好",
      "id": 961067500,
      "trackNumberUpdateTime": 1508178808255,
      "status": 0,
      "userId": 88644734,
      "createTime": 1508178807843,
      "updateTime": 1508375147949,
      "subscribedCount": 70,
      "trackCount": 50,
      "cloudTrackCount": 0,
      "coverImgUrl": "http://p1.music.126.net/QXFeLSYMoVilhugHj4gdRg==/109951163045987508.jpg",
      "coverImgId": 109951163045987508,
      "description": "认识一首歌，就像结识一个人。\n歌有多种的风格，人有多种的类型；歌有不同的旋律，人有不同的样貌；\n歌有多样的元素，人有多样的个性；歌有各样的意境，人有各样的想法。\n邂逅一首对的歌，就像相遇一个对的人，来之不易，充盈着的美好。",
      "tags": [
        "日语",
        "影视原声",
        "ACG"
      ],
      "playCount": 5404,
      "trackUpdateTime": 1508260836614,
      "specialType": 0,
      "totalDuration": 0,
      "creator": {
        "defaultAvatar": false,
        "province": 1000000,
        "authStatus": 0,
        "followed": false,
        "avatarUrl": "http://p1.music.126.net/_cvl1iQYkkWxwc8AM6u20g==/109951163043594555.jpg",
        "accountStatus": 0,
        "gender": 1,
        "city": 1003100,
        "birthday": 744620400000,
        "userId": 88644734,
        "userType": 0,
        "nickname": "Areal肥阳",
        "signature": "当个直男这么难？",
        "description": "",
        "detailDescription": "",
        "avatarImgId": 109951163043594555,
        "backgroundImgId": 18902803905082913,
        "backgroundUrl": "http://p1.music.126.net/19l8HdsfhyBTOxEiayKy5A==/18902803905082913.jpg",
        "authority": 0,
        "mutual": false,
        "expertTags": [
          "日语",
          "ACG",
          "电子"
        ],
        "experts": null,
        "djStatus": 10,
        "vipType": 10,
        "remarkName": null,
        "avatarImgIdStr": "109951163043594555",
        "backgroundImgIdStr": "18902803905082913",
        "avatarImgId_str": "109951163043594555"
      },
      "tracks": null,
      "subscribers": [
        {
          "defaultAvatar": false,
          "province": 440000,
          "authStatus": 0,
          "followed": false,
          "avatarUrl": "http://p1.music.126.net/7HrU774tKa5UGcB0tW_yPA==/18875316114326249.jpg",
          "accountStatus": 0,
          "gender": 1,
          "city": 441900,
          "birthday": 971835903234,
          "userId": 476193545,
          "userType": 0,
          "nickname": "枫林似焰",
          "signature": "",
          "description": "",
          "detailDescription": "",
          "avatarImgId": 18875316114326249,
          "backgroundImgId": 19019352137650967,
          "backgroundUrl": "http://p1.music.126.net/KDyHmPZ17trk5qHHldV4_Q==/19019352137650967.jpg",
          "authority": 0,
          "mutual": false,
          "expertTags": null,
          "experts": null,
          "djStatus": 0,
          "vipType": 0,
          "remarkName": null,
          "avatarImgIdStr": "18875316114326249",
          "backgroundImgIdStr": "19019352137650967",
          "avatarImgId_str": "18875316114326249"
        }
      ],
      "subscribed": null,
      "commentThreadId": "A_PL_0_961067500",
      "newImported": false,
      "adType": 0,
      "highQuality": false,
      "privacy": 0,
      "ordered": true,
      "anonimous": false,
      "shareCount": 3,
      "coverImgId_str": "109951163045987508",
      "commentCount": 4
    },
    {
      "name": "韩系柔情声线•众里寻他千百度",
      "id": 942978979,
      "trackNumberUpdateTime": 1508334919250,
      "status": 0,
      "userId": 315850166,
      "createTime": 1506991731994,
      "updateTime": 1508334919250,
      "subscribedCount": 54,
      "trackCount": 60,
      "cloudTrackCount": 0,
      "coverImgUrl": "http://p1.music.126.net/Iz1wtX1xuDGY8NaNyn596w==/18943485835342966.jpg",
      "coverImgId": 18943485835342966,
      "description": "↪如果要相爱的话\n↪那就是你\n↪像松露流进巧克力\n↪像冬日里的暖手心\n↪像雨天躲在被窝里\n↪温柔细腻的感情流淌在他的声线中\n↪真挚幸福的回忆徜徉在你的耳畔里",
      "tags": [
        "韩语",
        "流行",
        "R&B/Soul"
      ],
      "playCount": 6542,
      "trackUpdateTime": 1508338404404,
      "specialType": 0,
      "totalDuration": 0,
      "creator": {
        "defaultAvatar": false,
        "province": 1000000,
        "authStatus": 0,
        "followed": false,
        "avatarUrl": "http://p1.music.126.net/tXe-1Q1mlawoqnxmWyUUIA==/18701593278657384.jpg",
        "accountStatus": 0,
        "gender": 2,
        "city": 1010000,
        "birthday": -2209017600000,
        "userId": 315850166,
        "userType": 0,
        "nickname": "西柚甜-",
        "signature": "♡♡♡♡",
        "description": "",
        "detailDescription": "",
        "avatarImgId": 18701593278657384,
        "backgroundImgId": 18667508418271883,
        "backgroundUrl": "http://p1.music.126.net/irHC7SXqiuHBy1jpWVVwpg==/18667508418271883.jpg",
        "authority": 0,
        "mutual": false,
        "expertTags": null,
        "experts": null,
        "djStatus": 0,
        "vipType": 0,
        "remarkName": null,
        "avatarImgIdStr": "18701593278657384",
        "backgroundImgIdStr": "18667508418271883",
        "avatarImgId_str": "18701593278657384"
      },
      "tracks": null,
      "subscribers": [
        {
          "defaultAvatar": false,
          "province": 440000,
          "authStatus": 0,
          "followed": false,
          "avatarUrl": "http://p1.music.126.net/7HrU774tKa5UGcB0tW_yPA==/18875316114326249.jpg",
          "accountStatus": 0,
          "gender": 1,
          "city": 441900,
          "birthday": 971835903234,
          "userId": 476193545,
          "userType": 0,
          "nickname": "枫林似焰",
          "signature": "",
          "description": "",
          "detailDescription": "",
          "avatarImgId": 18875316114326249,
          "backgroundImgId": 19019352137650967,
          "backgroundUrl": "http://p1.music.126.net/KDyHmPZ17trk5qHHldV4_Q==/19019352137650967.jpg",
          "authority": 0,
          "mutual": false,
          "expertTags": null,
          "experts": null,
          "djStatus": 0,
          "vipType": 0,
          "remarkName": null,
          "avatarImgIdStr": "18875316114326249",
          "backgroundImgIdStr": "19019352137650967",
          "avatarImgId_str": "18875316114326249"
        }
      ],
      "subscribed": null,
      "commentThreadId": "A_PL_0_942978979",
      "newImported": false,
      "adType": 0,
      "highQuality": false,
      "privacy": 0,
      "ordered": true,
      "anonimous": false,
      "shareCount": 2,
      "coverImgId_str": "18943485835342966",
      "commentCount": 8
    }
  ],
  "code": 200,
  "more": true,
  "total": 1307
}